runtests.py
setup.py
simple_feedback/__init__.py
simple_feedback/admin.py
simple_feedback/apps.py
simple_feedback/models.py
simple_feedback/serializers.py
simple_feedback/urls.py
simple_feedback/views.py
simple_feedback/migrations/0001_initial.py
simple_feedback/migrations/0002_auto_20180115_1854.py
simple_feedback/migrations/0003_ticket_assignee.py
simple_feedback/migrations/0004_auto_20180612_1559.py
simple_feedback/migrations/0005_alter_ticket_meta.py
simple_feedback/migrations/__init__.py
django_simplefeedback-1.2.2.dist-info/METADATA
django_simplefeedback-1.2.2.dist-info/WHEEL
django_simplefeedback-1.2.2.dist-info/licenses/LICENSE
django_simplefeedback-1.2.2.dist-info/RECORD
