Metadata-Version: 2.1
Name: django-simplefeedback
Version: 1.2.2
Summary: A simple Django app to handle user tickets.
Project-URL: Homepage, https://github.com/pulilab/django-simple-feedback
Project-URL: Bug Tracker, https://github.com/pulilab/django-simple-feedback/issues
Author-email: Zoltan Ilcsik <zi@pulilab.com>, Fekete Gyorgy <f@pulilab.com>
License-File: LICENSE
Classifier: License :: OSI Approved :: MIT License
Classifier: Operating System :: OS Independent
Classifier: Programming Language :: Python :: 3
Requires-Python: >=3.7
